tenyks_sdk/__init__.py
tenyks_sdk/file_providers/__init__.py
tenyks_sdk/file_providers/config.py
tenyks_sdk/file_providers/data_classes.py
tenyks_sdk/file_providers/dataset_images_file_provider.py
tenyks_sdk/file_providers/dataset_images_file_provider_factory.py
tenyks_sdk/file_providers/dataset_metadata_file_provider.py
tenyks_sdk/file_providers/dataset_metadata_file_provider_factory.py
tenyks_sdk/file_providers/directory_provider.py
tenyks_sdk/file_providers/directory_provider_factory.py
tenyks_sdk/file_providers/file_resource_provider.py
tenyks_sdk/file_providers/file_resource_provider_factory.py
tenyks_sdk/file_providers/single_file_provider.py
tenyks_sdk/file_providers/single_file_provider_factory.py
tenyks_sdk/file_providers/storage_location_assembler.py
tenyks_sdk/file_providers/aws/aws_dataset_images_file_provider.py
tenyks_sdk/file_providers/aws/aws_dataset_metadata_file_provider.py
tenyks_sdk/file_providers/aws/aws_directory_provider.py
tenyks_sdk/file_providers/aws/aws_location_builder.py
tenyks_sdk/file_providers/aws/aws_single_file_provider.py
tenyks_sdk/file_providers/aws/aws_video_file_provider.py
tenyks_sdk/file_providers/aws/boto_s3_client_factory.py
tenyks_sdk/file_providers/aws/data_classes.py
tenyks_sdk/file_providers/aws/s3_client.py
tenyks_sdk/file_providers/aws/s3_resource_provider.py
tenyks_sdk/file_providers/aws/s3_url_parser.py
tenyks_sdk/file_providers/azure/azure_client.py
tenyks_sdk/file_providers/azure/azure_client_factory.py
tenyks_sdk/file_providers/azure/azure_dataset_images_file_provider.py
tenyks_sdk/file_providers/azure/azure_dataset_metadata_file_provider.py
tenyks_sdk/file_providers/azure/azure_directory_provider.py
tenyks_sdk/file_providers/azure/azure_location_builder.py
tenyks_sdk/file_providers/azure/azure_resource_provider.py
tenyks_sdk/file_providers/azure/azure_single_file_provider.py
tenyks_sdk/file_providers/azure/azure_url_parser.py
tenyks_sdk/file_providers/azure/data_classes.py
tenyks_sdk-2.0.4.dist-info/METADATA
tenyks_sdk-2.0.4.dist-info/WHEEL
tenyks_sdk-2.0.4.dist-info/top_level.txt
tenyks_sdk-2.0.4.dist-info/RECORD
