Metadata-Version: 2.4
Name: tenyks-sdk
Version: 2.0.4
Summary: Add your description here
Requires-Python: >=3.10
Requires-Dist: azure-storage-blob>=12.25.1
Requires-Dist: boto3>=1.38.23
Requires-Dist: dataclasses-json>=0.6.7
Requires-Dist: fastclasses-json>=0.8.0
Requires-Dist: google-cloud-storage>=3.1.0
Requires-Dist: ipywidgets>=8.1.7
Requires-Dist: opencv-python-headless>=4.11.0.86
Requires-Dist: pillow>=11.2.1
Requires-Dist: pydantic[email]>=2.11.5
Requires-Dist: requests>=2.32.3
Requires-Dist: rich>=14.0.0
Requires-Dist: urllib3>=2.4.0
Requires-Dist: werkzeug>=3.1.3
